odoo10_addon_cms_form-10.0.1.4.4-nspkg.pth
odoo/addons/cms_form/CHANGES.rst
odoo/addons/cms_form/README.rst
odoo/addons/cms_form/__init__.py
odoo/addons/cms_form/__manifest__.py
odoo/addons/cms_form/marshallers.py
odoo/addons/cms_form/utils.py
odoo/addons/cms_form/controllers/__init__.py
odoo/addons/cms_form/controllers/main.py
odoo/addons/cms_form/doc/Makefile
odoo/addons/cms_form/doc/source/basics.rst
odoo/addons/cms_form/doc/source/conf.py
odoo/addons/cms_form/doc/source/index.rst
odoo/addons/cms_form/doc/source/wizard.rst
odoo/addons/cms_form/doc/source/_static/images/cms_form_example_create_partner.png
odoo/addons/cms_form/doc/source/_static/images/cms_form_example_edit_partner.png
odoo/addons/cms_form/doc/source/_static/images/cms_form_example_fieldsets.png
odoo/addons/cms_form/doc/source/_static/images/cms_form_example_search.png
odoo/addons/cms_form/doc/source/_static/images/cms_form_example_tabbed.png
odoo/addons/cms_form/i18n/cms_form.pot
odoo/addons/cms_form/i18n/de.po
odoo/addons/cms_form/models/__init__.py
odoo/addons/cms_form/models/cms_form.py
odoo/addons/cms_form/models/cms_form_mixin.py
odoo/addons/cms_form/models/cms_form_wizard.py
odoo/addons/cms_form/models/cms_search_form.py
odoo/addons/cms_form/models/ir_qweb.py
odoo/addons/cms_form/models/test_models.py
odoo/addons/cms_form/models/website_mixin.py
odoo/addons/cms_form/models/widgets.py
odoo/addons/cms_form/security/cms_form.xml
odoo/addons/cms_form/static/description/icon.png
odoo/addons/cms_form/static/src/js/date_widget.js
odoo/addons/cms_form/static/src/js/lock_copy_paste.js
odoo/addons/cms_form/static/src/js/master_slave.js
odoo/addons/cms_form/static/src/js/select2widgets.js
odoo/addons/cms_form/static/src/js/textarea_widget.js
odoo/addons/cms_form/static/src/less/cms_form.less
odoo/addons/cms_form/static/src/less/progressbar.less
odoo/addons/cms_form/templates/assets.xml
odoo/addons/cms_form/templates/form.xml
odoo/addons/cms_form/templates/widgets.xml
odoo10_addon_cms_form-10.0.1.4.4.dist-info/METADATA
odoo10_addon_cms_form-10.0.1.4.4.dist-info/WHEEL
odoo10_addon_cms_form-10.0.1.4.4.dist-info/namespace_packages.txt
odoo10_addon_cms_form-10.0.1.4.4.dist-info/top_level.txt
odoo10_addon_cms_form-10.0.1.4.4.dist-info/RECORD
