Metadata-Version: 2.1
Name: odoo10-addon-cms-form
Version: 10.0.1.4.4
Summary: Basic content type form
Home-page: UNKNOWN
Author: Camptocamp, Odoo Community Association (OCA)
Author-email: support@odoo-community.org
License: LGPL-3
Platform: UNKNOWN
Classifier: Programming Language :: Python
Classifier: Framework :: Odoo
Classifier: License :: OSI Approved :: GNU Lesser General Public License v3 (LGPLv3)
Requires-Python: ~=2.7
Requires-Dist: odoo10-addon-cms-info
Requires-Dist: odoo10-addon-cms-status-message
Requires-Dist: odoo (<10.1dev,>=10.0)
